{
  "timestamp": 1763741616.590771,
  "headline": "Labour Codes trigger showdown, Unions call \u2018combative resistance\u2019 on Nov 26",
  "character": "chip",
  "segment_type": "headline",
  "synthesis": "This ties into broader market movement and sentiment.",
  "timeline": [
    {
      "type": "chip_open",
      "character": "chip",
      "voice_id": "teAyVVX8spybXkITa1A0",
      "text": "Good evening \u2014 here\u2019s what\u2019s moving markets.",
      "timestamp": 1763741615.1198926
    },
    {
      "type": "chip_analysis",
      "character": "chip",
      "voice_id": "teAyVVX8spybXkITa1A0",
      "text": "The short version is this: This ties into broader market movement and sentiment.. Underlying trend remains intact unless key levels break.",
      "timestamp": 1763741615.119929
    },
    {
      "type": "chip_transition",
      "character": "chip",
      "voice_id": "teAyVVX8spybXkITa1A0",
      "text": "Turning now to a developing labor dispute that is capturing widespread attention.",
      "timestamp": 1763741616.2407064
    },
    {
      "type": "chip_toss",
      "character": "chip",
      "voice_id": "teAyVVX8spybXkITa1A0",
      "text": "Reef, help us understand the on-chain angle.",
      "timestamp": 1763741616.2407262
    },
    {
      "type": "anchor_analysis",
      "character": "reef",
      "voice_id": "7pLXpsTZ3rOalpNWmYqI",
      "text": "This is a pressure cooker for liquidity. This ties into broader market movement and sentiment..",
      "timestamp": 1763741616.240743
    },
    {
      "type": "chip_toss",
      "character": "chip",
      "voice_id": "teAyVVX8spybXkITa1A0",
      "text": "Lawson, legally speaking \u2014 what does this mean?",
      "timestamp": 1763741616.240748
    },
    {
      "type": "anchor_analysis",
      "character": "lawson",
      "voice_id": "Wz0W8ilvy9oYu7DeKWfB",
      "text": "From a regulatory standpoint: This ties into broader market movement and sentiment..",
      "timestamp": 1763741616.2407558
    },
    {
      "type": "chip_toss",
      "character": "chip",
      "voice_id": "teAyVVX8spybXkITa1A0",
      "text": "Bond, how do global flows factor in?",
      "timestamp": 1763741616.2407591
    },
    {
      "type": "anchor_analysis",
      "character": "bond",
      "voice_id": "ckPPrwZqzA7Vp7ceNunQ",
      "text": "Liquidity is at an inflection: This ties into broader market movement and sentiment..",
      "timestamp": 1763741616.2407665
    },
    {
      "type": "vega_block",
      "character": "vega",
      "voice_id": "Ax1HxHll9ku8pGyIt6kK",
      "text": "Okay, real talk: This ties into broader market movement and. Everyone's pretending this isn't chaotic, but it",
      "timestamp": 1763741616.2407792
    },
    {
      "type": "bitsy_interrupt",
      "character": "bitsy",
      "voice_id": "VOkhRocQyiAQg2RF9A5e",
      "text": "Hi! Sorry! I know the show's serious right now but the soundboard button is glowing and",
      "timestamp": 1763741616.2407908
    },
    {
      "type": "chip_transition",
      "character": "chip",
      "voice_id": "teAyVVX8spybXkITa1A0",
      "text": "Turning now to developments shaping the labor landscape nationwide.",
      "timestamp": 1763741616.590723
    },
    {
      "type": "chip_reentry",
      "character": "chip",
      "voice_id": "teAyVVX8spybXkITa1A0",
      "text": "Grounding this in data:",
      "timestamp": 1763741616.5907419
    }
  ],
  "audio_blocks": [
    {
      "character": "chip",
      "voice_id": "teAyVVX8spybXkITa1A0",
      "block_type": "chip_open",
      "text": "Good evening \u2014 here\u2019s what\u2019s moving markets.",
      "content": "Good evening \u2014 here\u2019s what\u2019s moving markets.",
      "timestamp": 1763741615.1198957
    },
    {
      "character": "chip",
      "voice_id": "teAyVVX8spybXkITa1A0",
      "block_type": "chip_analysis",
      "text": "The short version is this: This ties into broader market movement and sentiment.. Underlying trend remains intact unless key levels break.",
      "content": "The short version is this: This ties into broader market movement and sentiment.. Underlying trend remains intact unless key levels break.",
      "timestamp": 1763741615.11993
    },
    {
      "character": "chip",
      "voice_id": "teAyVVX8spybXkITa1A0",
      "block_type": "chip_transition",
      "text": "Turning now to a developing labor dispute that is capturing widespread attention.",
      "content": "Turning now to a developing labor dispute that is capturing widespread attention.",
      "timestamp": 1763741616.2407095
    },
    {
      "character": "chip",
      "voice_id": "teAyVVX8spybXkITa1A0",
      "block_type": "chip_toss",
      "text": "Reef, help us understand the on-chain angle.",
      "content": "Reef, help us understand the on-chain angle.",
      "timestamp": 1763741616.240727
    },
    {
      "character": "reef",
      "voice_id": "7pLXpsTZ3rOalpNWmYqI",
      "block_type": "anchor_analysis",
      "text": "This is a pressure cooker for liquidity. This ties into broader market movement and sentiment..",
      "content": "This is a pressure cooker for liquidity. This ties into broader market movement and sentiment..",
      "timestamp": 1763741616.2407439
    },
    {
      "character": "chip",
      "voice_id": "teAyVVX8spybXkITa1A0",
      "block_type": "chip_toss",
      "text": "Lawson, legally speaking \u2014 what does this mean?",
      "content": "Lawson, legally speaking \u2014 what does this mean?",
      "timestamp": 1763741616.240749
    },
    {
      "character": "lawson",
      "voice_id": "Wz0W8ilvy9oYu7DeKWfB",
      "block_type": "anchor_analysis",
      "text": "From a regulatory standpoint: This ties into broader market movement and sentiment..",
      "content": "From a regulatory standpoint: This ties into broader market movement and sentiment..",
      "timestamp": 1763741616.2407563
    },
    {
      "character": "chip",
      "voice_id": "teAyVVX8spybXkITa1A0",
      "block_type": "chip_toss",
      "text": "Bond, how do global flows factor in?",
      "content": "Bond, how do global flows factor in?",
      "timestamp": 1763741616.2407598
    },
    {
      "character": "bond",
      "voice_id": "ckPPrwZqzA7Vp7ceNunQ",
      "block_type": "anchor_analysis",
      "text": "Liquidity is at an inflection: This ties into broader market movement and sentiment..",
      "content": "Liquidity is at an inflection: This ties into broader market movement and sentiment..",
      "timestamp": 1763741616.2407672
    },
    {
      "character": "vega",
      "voice_id": "Ax1HxHll9ku8pGyIt6kK",
      "block_type": "vega_block",
      "text": "Okay, real talk: This ties into broader market movement and. Everyone's pretending this isn't chaotic, but it",
      "content": "Okay, real talk: This ties into broader market movement and. Everyone's pretending this isn't chaotic, but it",
      "timestamp": 1763741616.2407806
    },
    {
      "character": "bitsy",
      "voice_id": "VOkhRocQyiAQg2RF9A5e",
      "block_type": "bitsy_interrupt",
      "text": "Hi! Sorry! I know the show's serious right now but the soundboard button is glowing and",
      "content": "Hi! Sorry! I know the show's serious right now but the soundboard button is glowing and",
      "timestamp": 1763741616.240792
    },
    {
      "character": "chip",
      "voice_id": "teAyVVX8spybXkITa1A0",
      "block_type": "chip_transition",
      "text": "Turning now to developments shaping the labor landscape nationwide.",
      "content": "Turning now to developments shaping the labor landscape nationwide.",
      "timestamp": 1763741616.590727
    },
    {
      "character": "chip",
      "voice_id": "teAyVVX8spybXkITa1A0",
      "block_type": "chip_reentry",
      "text": "Grounding this in data:",
      "content": "Grounding this in data:",
      "timestamp": 1763741616.5907433
    }
  ],
  "unreal": {
    "scene_id": "scene_1763741616",
    "engine_version": "UE5.3+",
    "camera_plan": "two_shot_chip_anchor",
    "characters": [
      "chip",
      "reef",
      "lawson",
      "bond",
      "vega",
      "bitsy"
    ],
    "shot_plan": [
      {
        "shot": "chip_intro",
        "camera": "chip_close"
      },
      {
        "shot": "primary_analysis",
        "camera": "chip_mid"
      },
      {
        "shot": "anchor_1",
        "camera": "anchor_close"
      },
      {
        "shot": "anchor_2",
        "camera": "anchor_close"
      },
      {
        "shot": "vega",
        "camera": "chaos_cut"
      },
      {
        "shot": "bitsy",
        "camera": "bitsy_pop"
      },
      {
        "shot": "chip_reentry",
        "camera": "chip_mid"
      },
      {
        "shot": "outro",
        "camera": "chip_close"
      }
    ],
    "audio_tracks": [
      {
        "character": "chip",
        "voice_id": "teAyVVX8spybXkITa1A0",
        "text": "Good evening \u2014 here\u2019s what\u2019s moving markets.",
        "block_type": "chip_open",
        "timestamp": 1763741615.1198926
      },
      {
        "character": "chip",
        "voice_id": "teAyVVX8spybXkITa1A0",
        "text": "The short version is this: This ties into broader market movement and sentiment.. Underlying trend remains intact unless key levels break.",
        "block_type": "chip_analysis",
        "timestamp": 1763741615.119929
      },
      {
        "character": "chip",
        "voice_id": "teAyVVX8spybXkITa1A0",
        "text": "Turning now to a developing labor dispute that is capturing widespread attention.",
        "block_type": "chip_transition",
        "timestamp": 1763741616.2407064
      },
      {
        "character": "chip",
        "voice_id": "teAyVVX8spybXkITa1A0",
        "text": "Reef, help us understand the on-chain angle.",
        "block_type": "chip_toss",
        "timestamp": 1763741616.2407262
      },
      {
        "character": "reef",
        "voice_id": "7pLXpsTZ3rOalpNWmYqI",
        "text": "This is a pressure cooker for liquidity. This ties into broader market movement and sentiment..",
        "block_type": "anchor_analysis",
        "timestamp": 1763741616.240743
      },
      {
        "character": "chip",
        "voice_id": "teAyVVX8spybXkITa1A0",
        "text": "Lawson, legally speaking \u2014 what does this mean?",
        "block_type": "chip_toss",
        "timestamp": 1763741616.240748
      },
      {
        "character": "lawson",
        "voice_id": "Wz0W8ilvy9oYu7DeKWfB",
        "text": "From a regulatory standpoint: This ties into broader market movement and sentiment..",
        "block_type": "anchor_analysis",
        "timestamp": 1763741616.2407558
      },
      {
        "character": "chip",
        "voice_id": "teAyVVX8spybXkITa1A0",
        "text": "Bond, how do global flows factor in?",
        "block_type": "chip_toss",
        "timestamp": 1763741616.2407591
      },
      {
        "character": "bond",
        "voice_id": "ckPPrwZqzA7Vp7ceNunQ",
        "text": "Liquidity is at an inflection: This ties into broader market movement and sentiment..",
        "block_type": "anchor_analysis",
        "timestamp": 1763741616.2407665
      },
      {
        "character": "vega",
        "voice_id": "Ax1HxHll9ku8pGyIt6kK",
        "text": "Okay, real talk: This ties into broader market movement and. Everyone's pretending this isn't chaotic, but it",
        "block_type": "vega_block",
        "timestamp": 1763741616.2407792
      },
      {
        "character": "bitsy",
        "voice_id": "VOkhRocQyiAQg2RF9A5e",
        "text": "Hi! Sorry! I know the show's serious right now but the soundboard button is glowing and",
        "block_type": "bitsy_interrupt",
        "timestamp": 1763741616.2407908
      },
      {
        "character": "chip",
        "voice_id": "teAyVVX8spybXkITa1A0",
        "text": "Turning now to developments shaping the labor landscape nationwide.",
        "block_type": "chip_transition",
        "timestamp": 1763741616.590723
      },
      {
        "character": "chip",
        "voice_id": "teAyVVX8spybXkITa1A0",
        "text": "Grounding this in data:",
        "block_type": "chip_reentry",
        "timestamp": 1763741616.5907419
      }
    ],
    "duration_seconds": 41.6
  }
}